CHANGES.txt
CONTRIBUTORS.txt
MANIFEST.in
README.txt
setup.cfg
setup.py
collective/__init__.py
collective.signableevent.egg-info/PKG-INFO
collective.signableevent.egg-info/PKG-INFO~
collective.signableevent.egg-info/SOURCES.txt
collective.signableevent.egg-info/dependency_links.txt
collective.signableevent.egg-info/entry_points.txt
collective.signableevent.egg-info/namespace_packages.txt
collective.signableevent.egg-info/not-zip-safe
collective.signableevent.egg-info/paster_plugins.txt
collective.signableevent.egg-info/requires.txt
collective.signableevent.egg-info/top_level.txt
collective/signableevent/AUTHORS
collective/signableevent/COPYING
collective/signableevent/README.txt
collective/signableevent/__init__.py
collective/signableevent/config.py
collective/signableevent/configure.zcml
collective/signableevent/csvsigners.py
collective/signableevent/events.py
collective/signableevent/monkey.py
collective/signableevent/skins.zcml
collective/signableevent/utils.py
collective/signableevent/workflowgraph.py
collective/signableevent/browser/__init__.py
collective/signableevent/browser/configure.zcml
collective/signableevent/browser/templates/signable_event_signers.pt
collective/signableevent/browser/templates/signable_event_view.pt
collective/signableevent/browser/templates/signable_view_threads.pt
collective/signableevent/browser/templates/signableevents_allsigned_csv.pt
collective/signableevent/content/__init__.py
collective/signableevent/content/configure.zcml
collective/signableevent/content/eventsignup.py
collective/signableevent/content/signableevent.py
collective/signableevent/interfaces/__init__.py
collective/signableevent/interfaces/eventsignup.py
collective/signableevent/interfaces/signableevent.py
collective/signableevent/locales/plone.pot
collective/signableevent/locales/signableevent.pot
collective/signableevent/locales/fr/LC_MESSAGES/plone.mo
collective/signableevent/locales/fr/LC_MESSAGES/plone.po
collective/signableevent/locales/fr/LC_MESSAGES/signableevent.mo
collective/signableevent/locales/fr/LC_MESSAGES/signableevent.po
collective/signableevent/locales/it/LC_MESSAGES/README.txt
collective/signableevent/locales/it/LC_MESSAGES/plone.mo
collective/signableevent/locales/it/LC_MESSAGES/plone.po
collective/signableevent/locales/it/LC_MESSAGES/signableevent.mo
collective/signableevent/locales/it/LC_MESSAGES/signableevent.po
collective/signableevent/portlets/__init__.py
collective/signableevent/portlets/configure.zcml
